ganache_python_service/__init__.py
ganache_python_service/ganache_service.py
ganache_python_service/helpers.py
ganache_python_service/logger.py
ganache_python_serv-0.3.1.dist-info/LICENSE
ganache_python_serv-0.3.1.dist-info/METADATA
ganache_python_serv-0.3.1.dist-info/WHEEL
ganache_python_serv-0.3.1.dist-info/top_level.txt
ganache_python_serv-0.3.1.dist-info/RECORD
