Metadata-Version: 2.1
Name: ganache-python-serv
Version: 0.3.1
Summary: Library to interact directly with ganache
Home-page: https://github.com/Bortxop/ganache-python-service
Author: Borja León
Author-email: borja.l.murua@gmail.com
License: MIT
Keywords: ganache,python,ethereum,blockchain,testing
License-File: LICENSE
Requires-Dist: psutil
